content_core/__init__.py
content_core/cc_config.yaml
content_core/config.py
content_core/logging.py
content_core/models.py
content_core/models_config.yaml
content_core/py.typed
content_core/templated_message.py
content_core/common/CLAUDE.md
content_core/common/__init__.py
content_core/common/exceptions.py
content_core/common/retry.py
content_core/common/state.py
content_core/common/types.py
content_core/common/utils.py
content_core/content/__init__.py
content_core/content/cleanup/__init__.py
content_core/content/cleanup/core.py
content_core/content/extraction/__init__.py
content_core/content/extraction/graph.py
content_core/content/identification/__init__.py
content_core/content/identification/file_detector.py
content_core/content/summary/__init__.py
content_core/content/summary/core.py
content_core/mcp/__init__.py
content_core/mcp/server.py
content_core/notebooks/run.ipynb
content_core/notebooks/urls.ipynb
content_core/processors/CLAUDE.md
content_core/processors/audio.py
content_core/processors/docling.py
content_core/processors/office.py
content_core/processors/pdf.py
content_core/processors/text.py
content_core/processors/url.py
content_core/processors/video.py
content_core/processors/youtube.py
content_core/tools/CLAUDE.md
content_core/tools/__init__.py
content_core/tools/cleanup.py
content_core/tools/extract.py
content_core/tools/summarize.py
content_core-1.14.1.dist-info/METADATA
content_core-1.14.1.dist-info/WHEEL
content_core-1.14.1.dist-info/entry_points.txt
content_core-1.14.1.dist-info/licenses/LICENSE
content_core-1.14.1.dist-info/RECORD
