Metadata-Version: 2.4
Name: content-core
Version: 1.14.1
Summary: Extract what matters from any media source. Available as Python Library, macOS Service, CLI and MCP Server
Author-email: LUIS NOVO <lfnovo@gmail.com>
License-File: LICENSE
Requires-Python: >=3.10
Requires-Dist: ai-prompter>=0.2.3
Requires-Dist: aiohttp>=3.11
Requires-Dist: asciidoc>=10.2.1
Requires-Dist: bs4>=0.0.2
Requires-Dist: dicttoxml>=1.7.16
Requires-Dist: esperanto>=2.17.0
Requires-Dist: fastmcp>=2.10.0
Requires-Dist: firecrawl-py>=2.7.0
Requires-Dist: jinja2>=3.1.6
Requires-Dist: langdetect>=1.0.9
Requires-Dist: langgraph>=1.0.0
Requires-Dist: loguru>=0.7.3
Requires-Dist: markdownify>=0.12.1
Requires-Dist: moviepy>=2.1.2
Requires-Dist: openpyxl>=3.1.5
Requires-Dist: pandas>=2.2.3
Requires-Dist: pillow>=10.4.0
Requires-Dist: pymupdf>=1.25.5
Requires-Dist: python-docx>=1.1.2
Requires-Dist: python-dotenv>=1.1.0
Requires-Dist: python-pptx>=1.0.2
Requires-Dist: pytubefix>=9.1.1
Requires-Dist: readability-lxml>=0.8.4.1
Requires-Dist: tenacity>=8.0.0
Requires-Dist: validators>=0.34.0
Requires-Dist: youtube-transcript-api>=1.0.3
Provides-Extra: crawl4ai
Requires-Dist: crawl4ai>=0.7.0; extra == 'crawl4ai'
Provides-Extra: docling
Requires-Dist: docling>=2.34.0; extra == 'docling'
